{
  "relatedQuestions": [
    {
      "relatedQuestionStrings": {
        "en": null,
        "de": "Wir bitten Sie nun, uns in dem folgenden Schema einen Überblick Ihres Werdegangs von Juli 2008 bis Dezember 2012 zu geben."
      },
      "questionNumber": "2.1",
      "instrumentNumber": 3
    }
  ],
  "distribution": {
    "statistics": {
      "meanDeviation": null,
      "mode": "1",
      "highWhisker": null,
      "lowWhisker": null,
      "thirdQuartile": null,
      "firstQuartile": null,
      "standardDeviation": null,
      "median": null,
      "kurtosis": null,
      "skewness": null,
      "maximum": null,
      "minimum": null,
      "meanValue": null
    },
    "missings": [
      {
        "label": {
          "en": "no answer",
          "de": "keine Angabe"
        },
        "relativeFrequency": 7.94,
        "absoluteFrequency": 2237,
        "code": -998
      },
      {
        "label": {
          "en": "not participated (panel)",
          "de": "keine Teilnahme (Panel)"
        },
        "relativeFrequency": 86.97,
        "absoluteFrequency": 24511,
        "code": -995
      },
      {
        "label": {
          "en": "does not apply",
          "de": "trifft nicht zu"
        },
        "relativeFrequency": 0.15,
        "absoluteFrequency": 41,
        "code": -988
      },
      {
        "label": {
          "en": "unknown missing",
          "de": "unbekannter fehlender Wert"
        },
        "relativeFrequency": 0.01,
        "absoluteFrequency": 2,
        "code": -969
      }
    ],
    "validResponses": [
      {
        "label": {
          "en": "no university study at one of the institutions (Uni or college of edu. or theological college …), but BA study",
          "de": "kein Studium an Uni/PH/KunstHS/Theol.HS/FH/VerwFH, aber Studium an BA"
        },
        "validRelativeFrequency": 1.44,
        "relativeFrequency": 0.07,
        "absoluteFrequency": 20,
        "value": "-944"
      },
      {
        "label": {
          "en": "university",
          "de": "Universität"
        },
        "validRelativeFrequency": 69.37,
        "relativeFrequency": 3.42,
        "absoluteFrequency": 965,
        "value": "1"
      },
      {
        "label": {
          "en": "college of education",
          "de": "Pädagogische Hochschulen"
        },
        "validRelativeFrequency": 0.86,
        "relativeFrequency": 0.04,
        "absoluteFrequency": 12,
        "value": "2"
      },
      {
        "label": {
          "en": "theological college",
          "de": "Theologische/Kirchliche Hochschulen"
        },
        "validRelativeFrequency": 0.07,
        "relativeFrequency": 0,
        "absoluteFrequency": 1,
        "value": "3"
      },
      {
        "label": {
          "en": "art colleges",
          "de": "Kunsthochschulen"
        },
        "validRelativeFrequency": 0.58,
        "relativeFrequency": 0.03,
        "absoluteFrequency": 8,
        "value": "4"
      },
      {
        "label": {
          "en": "university of applied sciences",
          "de": "Fachhochschule"
        },
        "validRelativeFrequency": 24.95,
        "relativeFrequency": 1.23,
        "absoluteFrequency": 347,
        "value": "5"
      },
      {
        "label": {
          "en": "colleges of public administration",
          "de": "Verwaltungsfachhochschulen"
        },
        "validRelativeFrequency": 2.73,
        "relativeFrequency": 0.13,
        "absoluteFrequency": 38,
        "value": "6"
      }
    ],
    "totalValidRelativeFrequency": 4.94,
    "totalValidAbsoluteFrequency": 1391,
    "totalAbsoluteFrequency": 28182
  },
  "filterDetails": {
    "expressionLanguage": null,
    "description": {
      "en": null,
      "de": null
    },
    "expression": null
  },
  "generationDetails": {
    "ruleExpressionLanguage": null,
    "rule": null,
    "description": {
      "en": "The type of higher education institution was generated from the coded data on institutions of higher education. The Destatis key directory for student and examination statistics (winter semester 2007/08) (see cl-destatis-studienfach-2008) was used for the classification. In the official statistics, missing universities were added and allocated from the project.",
      "de": "Die Hochschulart wurde aus den codierten Hochschulangaben generiert. Für die Zuordnung von Hochschulen zu der Hochschulart wurde das Destatis Schlüsselverzeichnis für die Studenten- und Prüfungsstatistik (WiSe 2007/08) (cl-destatis-hochschule-2008) verwendet. In der amtlichen Statistik fehlende Hochschulen wurden ergänzt und vom Projekt zugeordnet."
    }
  },
  "storageType": "integer",
  "relatedVariables": null,
  "doNotDisplayThousandsSeparator": false,
  "derivedVariablesIdentifier": "gsl2008-ds1-cstu212d",
  "panelIdentifier": null,
  "surveyNumbers": [3],
  "indexInDataSet": 523,
  "accessWays": ["onsite-suf"],
  "annotations": {
    "en": null,
    "de": null
  },
  "label": {
    "en": "2nd activity: type of higher education institution",
    "de": "2. Tätigkeit: Hochschulart"
  },
  "scaleLevel": {
    "en": "nominal",
    "de": "nominal"
  },
  "dataType": {
    "en": "numeric",
    "de": "numerisch"
  }
}
