{
	"surveyNumbers" : [
		1
	],
	"dataType" : {
		"de" : "numerisch",
		"en" : "numeric"
	},
	"scaleLevel" : {
		"de" : "ordinal",
		"en" : "ordinal"
	},
	"label" : {
		"de" : "Mathe (Fach): verständlich",
		"en" : null
	},
	"relatedQuestions" : [
		{
			"instrumentNumber" : 1,
			"questionNumber" : "04",
			"relatedQuestionStrings" : {
				"de" : "Der Unterricht der letzten beiden Schuljahre kann unter verschiedenen Gesichtspunkten bewertet werden:\nDer Unterricht im Fach Mathematik war…\nverständlich",
				"en" : null
			}
		}
	],
	"distribution" : {
		"totalAbsoluteFrequency" : 28182,
		"totalValidAbsoluteFrequency" : 27655,
		"totalValidRelativeFrequency" : 98.13,
		"histogram" : {
			"numberOfBins" : null,
			"start" : null,
			"end" : null
		},
		"statistics" : {
			"meanValue" : null,
			"minimum" : "1",
			"maximum" : "5",
			"skewness" : null,
			"kurtosis" : null,
			"median" : "3",
			"mode" : "2",
			"standardDeviation" : null,
			"deviance" : "3.10690738741271",
			"meanDeviation" : "2284.6866",
			"firstQuartile" : "2",
			"thirdQuartile" : "4",
			"lowWhisker" : 1,
			"highWhisker" : 5
		},
		"missings" : [
			{
				"code" : -999,
				"label" : {
					"de" : "weiß nicht",
					"en" : null
				},
				"relativeFrequency" : 0.64,
				"absoluteFrequency" : 179
			},
			{
				"code" : -998,
				"label" : {
					"de" : "keine Angabe",
					"en" : null
				},
				"relativeFrequency" : 1.23,
				"absoluteFrequency" : 348
			}
		],
		"validResponses" : [
			{
				"value" : "1",
				"label" : {
					"de" : "trifft voll zu",
					"en" : null
				},
				"relativeFrequency" : 16.12,
				"absoluteFrequency" : 4542,
				"validRelativeFrequency" : 16.42
			},
			{
				"value" : "2",
				"label" : {
					"de" : "2",
					"en" : null
				},
				"relativeFrequency" : 28.2,
				"absoluteFrequency" : 7947,
				"validRelativeFrequency" : 28.74
			},
			{
				"value" : "3",
				"label" : {
					"de" : "3",
					"en" : null
				},
				"relativeFrequency" : 26.27,
				"absoluteFrequency" : 7403,
				"validRelativeFrequency" : 26.77
			},
			{
				"value" : "4",
				"label" : {
					"de" : "4",
					"en" : null
				},
				"relativeFrequency" : 16.51,
				"absoluteFrequency" : 4652,
				"validRelativeFrequency" : 16.82
			},
			{
				"value" : "5",
				"label" : {
					"de" : "trifft gar nicht zu",
					"en" : null
				},
				"relativeFrequency" : 11.04,
				"absoluteFrequency" : 3111,
				"validRelativeFrequency" : 11.25
			}
		]
	}
}