{
	"surveyNumbers" : [
		3
	],
	"dataType" : {
		"de" : "numerisch",
		"en" : "numeric"
	},
	"storageType" : "integer",
	"scaleLevel" : {
		"de" : "nominal",
		"en" : "nominal"
	},
	"label" : {
		"de" : "Zeitpunkt Entscheidung Masterstudium",
		"en" : null
	},
	"relatedQuestions" : [
		{
			"instrumentNumber" : 3,
			"questionNumber" : "5.4",
			"relatedQuestionStrings" : {
				"de" : "Wann haben Sie sich für das Masterstudium entschieden?",
				"en" : null
			}
		}
	],
	"distribution" : {
		"totalAbsoluteFrequency" : 28182,
		"totalValidAbsoluteFrequency" : 1641,
		"totalValidRelativeFrequency" : 5.82,
		"histogram" : {
			"numberOfBins" : null,
			"start" : null,
			"end" : null
		},
		"statistics" : {
			"meanValue" : null,
			"minimum" : null,
			"maximum" : null,
			"skewness" : null,
			"kurtosis" : null,
			"median" : null,
			"mode" : "1",
			"standardDeviation" : null,
			"deviance" : "2.53579852587584",
			"meanDeviation" : null,
			"firstQuartile" : null,
			"thirdQuartile" : null,
			"lowWhisker" : null,
			"highWhisker" : null
		},
		"missings" : [
			{
				"code" : -998,
				"label" : {
					"de" : "keine Angabe",
					"en" : null
				},
				"relativeFrequency" : 0.3,
				"absoluteFrequency" : 85
			},
			{
				"code" : -995,
				"label" : {
					"de" : "keine Teilnahme (Panel)",
					"en" : null
				},
				"relativeFrequency" : 86.97,
				"absoluteFrequency" : 24511
			},
			{
				"code" : -989,
				"label" : {
					"de" : "filterbedingt fehlend",
					"en" : null
				},
				"relativeFrequency" : 6.9,
				"absoluteFrequency" : 1945
			}
		],
		"validResponses" : [
			{
				"value" : "1",
				"label" : {
					"de" : "vor Beginn des vorangegangenen Studiums",
					"en" : null
				},
				"relativeFrequency" : 2.59,
				"absoluteFrequency" : 729,
				"validRelativeFrequency" : 44.42
			},
			{
				"value" : "2",
				"label" : {
					"de" : "in den ersten beiden Semestern",
					"en" : null
				},
				"relativeFrequency" : 0.93,
				"absoluteFrequency" : 263,
				"validRelativeFrequency" : 16.03
			},
			{
				"value" : "3",
				"label" : {
					"de" : "erst später im Studium",
					"en" : null
				},
				"relativeFrequency" : 1.57,
				"absoluteFrequency" : 443,
				"validRelativeFrequency" : 27
			},
			{
				"value" : "4",
				"label" : {
					"de" : "weiß ich nicht",
					"en" : null
				},
				"relativeFrequency" : 0.73,
				"absoluteFrequency" : 206,
				"validRelativeFrequency" : 12.55
			}
		]
	}
}